nortrom/__init__.py
nortrom/__main__.py
nortrom-1.0.1.dist-info/METADATA
nortrom-1.0.1.dist-info/WHEEL
nortrom-1.0.1.dist-info/entry_points.txt
nortrom-1.0.1.dist-info/licenses/LICENSE.txt
nortrom-1.0.1.dist-info/RECORD
