Metadata-Version: 2.3
Name: nortrom
Version: 1.0.1
Summary: Discord bot to mute/deafen people
Project-URL: Repository, https://forge.steffo.eu/steffo/nortrom/
Author-email: Stefano Pigozzi <me@steffo.eu>
Maintainer-email: Stefano Pigozzi <me@steffo.eu>
License-Expression: EUPL-1.2
License-File: LICENSE.txt
Keywords: deafen,discord,mute,voice
Classifier: Development Status :: 5 - Production/Stable
Classifier: Operating System :: OS Independent
Classifier: Programming Language :: Python :: 3.9
Requires-Python: >=3.9
Requires-Dist: discord-py-slash-command~=1.1
Requires-Dist: discord-py~=1.6
